pyscgen/__config/__init__.py
pyscgen/__config/dtype_config.py
pyscgen/__init__.py
pyscgen/avro/__init__.py
pyscgen/avro/_model/__init__.py
pyscgen/avro/_model/__model_config.py
pyscgen/avro/_model/record_model.py
pyscgen/avro/schema/__init__.py
pyscgen/avro/schema/create_schema.py
pyscgen/json/__init__.py
pyscgen/json/_model/__init__.py
pyscgen/json/_model/__model_config.py
pyscgen/json/_model/analyze_model.py
pyscgen/json/_model/datatype_model.py
pyscgen/json/_model/document_model.py
pyscgen/json/analyze/__init__.py
pyscgen/json/analyze/analyze_documents.py
pyscgen/json/merge/__init__.py
pyscgen/json/merge/merge_documents.py
pyscgen/pydantic/__init__.py
pyscgen/pydantic/schema/__init__.py
pyscgen/pydantic/schema/create_schema.py
pyscgen-0.2.1.dist-info/LICENSE
pyscgen-0.2.1.dist-info/WHEEL
pyscgen-0.2.1.dist-info/METADATA
pyscgen-0.2.1.dist-info/RECORD
