Metadata-Version: 2.1
Name: pyscgen
Version: 0.2.1
Summary: Python AVRO Schema generator which can use multiples example JSONs as input to infer the Schema.
Home-page: https://github.com/Salfiii/pyscgen
License: BSD-3-Clause
Keywords: AVRO,JSON,merge,analyze,pydantic,model,schema,generator
Author: Florian Salfenmoser
Author-email: florian.salfenmoser.dev@outlook.de
Requires-Python: >=3.10,<4.0
Classifier: License :: OSI Approved :: BSD License
Classifier: Programming Language :: Python :: 3
Classifier: Programming Language :: Python :: 3.10
Classifier: Programming Language :: Python :: 3.11
Requires-Dist: glom (>=22.1.0,<23.0.0)
Requires-Dist: pandas (>=1.4.1,<2.0.0)
Requires-Dist: pydantic (>=1.9.0,<2.0.0)
Requires-Dist: pydantic-avro (>=0.4.2,<0.5.0)
Requires-Dist: shortuuid (>=1.0.8,<2.0.0)
Project-URL: Repository, https://github.com/Salfiii/pyscgen
